{
  "vpc-provider:account=916994818137:filter.vpc-id=vpc-0b534acf5457a44ea:region=us-east-1:returnAsymmetricSubnets=true": {
    "vpcId": "vpc-0b534acf5457a44ea",
    "vpcCidrBlock": "10.0.0.0/16",
    "ownerAccountId": "916994818137",
    "availabilityZones": [],
    "subnetGroups": [
      {
        "name": "Public",
        "type": "Public",
        "subnets": [
          {
            "subnetId": "subnet-0703871201568cc4d",
            "cidr": "10.0.0.0/18",
            "availabilityZone": "us-east-1a",
            "routeTableId": "rtb-04dbfc2dbaf0bee36"
          }
        ]
      }
    ]
  },
  "ami:account=916994818137:filters.image-type.0=machine:filters.name.0=RHEL-9*_HVM-*-x86_64-*:filters.state.0=available:owners.0=309956199498:region=us-east-1": "ami-0da265867ccdd23bd"
}
